kasumi/__init__.py
kasumi/applications.py
kasumi/cli/__core.py
kasumi/cli/__init__.py
kasumi/cli/__templates/default/main.py
kasumi/cli/__templates/default/manifest.json
kasumi/cli/__templates/default/requirements.txt
kasumi/cli/__templates/with_gear/main.py
kasumi/cli/__templates/with_gear/manifest.json
kasumi/cli/__templates/with_gear/requirements.txt
kasumi/cli/__templates/with_gear/src/sub.py
kasumi/exceptions.py
kasumi/gear.py
kasumi/models/asgi.py
kasumi/models/connection.py
kasumi/models/websocket.py
kasumi/responses.py
kasumi/websocket.py
kasumi_web-0.2.0.dist-info/METADATA
kasumi_web-0.2.0.dist-info/WHEEL
kasumi_web-0.2.0.dist-info/entry_points.txt
kasumi_web-0.2.0.dist-info/licenses/LICENSE
kasumi_web-0.2.0.dist-info/RECORD
