Metadata-Version: 2.1
Name: kasumi-web
Version: 0.2.0
Summary: Another ASGI Web framework.
Author-Email: AmaseCocoa <amase.cocoa@gmail.com>
License: MIT License
Project-URL: Repository, https://github.com/AmaseCocoa/Kasumi/
Requires-Python: >=3.10
Requires-Dist: starlette>=0.37.2
Requires-Dist: typer>=0.12.3
Requires-Dist: requests>=2.32.3
Requires-Dist: tqdm>=4.66.4
Requires-Dist: cowsay>=6.1
Requires-Dist: pydantic>=2.8.2
Requires-Dist: yarl>=1.9.4
Requires-Dist: pytest>=8.2.2; extra == "test"
Requires-Dist: ruff>=0.4.8; extra == "test"
Requires-Dist: httpx>=0.27.0; extra == "test"
Requires-Dist: uvicorn>=0.30.1; extra == "test"
Requires-Dist: pytest-asyncio>=0.23.7; extra == "test"
Provides-Extra: test
